{
  "product": [

    {
      "id": 1,
      "name": "life service",
      "service": "Cleaning",
      "price": "600",
      "catagory": "all  Cleaning service",
      "imformation": "Home Cleaning can do all home work include home serice",
      "imformations": "all in one catagory"
    },
    {
      "id": 2,
      "name": "velocity service",
      "service": "Cleaning",
      "price": 600,
      "catagory": "all Cleaning service",
      "imformation": "Home Cleaning can do all home work include home serice",
      "imformations": "all in one catagory"
    },
    {
      "id": 6,
      "name": "reac js  service",
      "service": "Cleaning",
      "price": 600,
      "catagory": "all service",
      "imformation": "Home Cleaning can do all home work include home serice",
      "imformations": "all in one catagory"
    },
    {
      "id": 7,
      "name": "react service",
      "service": "Cleaning",
      "price": 600,
      "catagory": "all service",
      "imformation": "Home Cleaning can do all home work include home serice",
      "imformations": "all in one catagory"
    },
    {
      "id": 8,
      "name": "lll service",
      "service": "Cleaning",
      "price": 600,
      "catagory": "all service",
      "imformation": "Home Cleaning can do all home work include home serice",
      "imformations": "all in one catagory"
    },
    {
      "id": 9,
      "name": "life service",
      "service": "Cleaning",
      "price": 600,
      "catagory": "all service",
      "imformation": "Home Cleaning can do all home work include home serice",
      "imformations": "all in one catagory"
    },
    {
      "id": 10,
      "name": "Lfide service",
      "service": "Cleaning",
      "price": 600,
      "catagory": "all service",
      "imformation": "Home Cleaning can do all home work include home serice",
      "imformations": "all in one catagory"
    },
    {
      "id": 11,
      "name": "velocity service",
      "service": "Cleaning",
      "price": 600,
      "catagory": "all service",
      "imformation": "Home Cleaning can do all home work include home serice",
      "imformations": "all in one catagory"
    },
    {
      "id": 12,
      "name": "lidecity service",
      "service": "Cleaning",
      "price": 600,
      "catagory": "all service",
      "imformation": "Home Cleaning can do all home work include home serice",
      "imformations": "all in one catagory"
    },
    {
      "id": 13,
      "name": "lifecity service",
      "service": "Cleaning",
      "price": 600,
      "catagory": "all service",
      "imformation": "Home Cleaning can do all home work include home serice",
      "imformations": "all in one catagory"
    },
    {
      "id": 14,
      "name": "city service",
      "service": "Cleaning",
      "price": 600,
      "catagory": "all service",
      "imformation": "Home Cleaning can do all home work include home serice",
      "imformations": "all in one catagory"
    },
    {
      "id": 15,
      "name": "omkar service",
      "service": "Driver",
      "price": 800,
      "catagory": "Driving for day",
      "imformation": "professional driving service by RazeJobfinder",
      "imformations": "For day only"
    },
    {
      "id": 16,
      "name": "akshay serives",
      "service": "Cleaning",
      "price": 600,
      "catagory": "Driving for day",
      "imformation": "professional driving service by RazeJobfinder",
      "imformations": "all in one catagory"
    },
    {
      "id": 17,
      "name": "kcuh bhi",
      "service": "Driver",
      "price": 600,
      "catagory": "Driving for day",
      "imformation": "professional driving service by RazeJobfinder",
      "imformations": "all in one catagory"
    },
    {
      "id": 18,
      "name": "kcuh bhi",
      "service": "Driver",
      "price": 600,
      "catagory": "Driving for day",
      "imformation": "professional driving service by RazeJobfinder",
      "imformations": "all in one catagory"
    },
    {
      "id": 19,
      "name": "kcuh bhi",
      "service": "Driver",
      "price": 600,
      "catagory": "Driving for day",
      "imformation": "professional driving service by RazeJobfinder",
      "imformations": "all in one catagory"
    },
    {
      "id": 20,
      "name": "kcuh bhi",
      "service": "Driver",
      "price": 900,
      "catagory": "Driving for day",
      "imformation": "professional driving service by RazeJobfinder",
      "imformations": "all in one catagory"
    },
    {
      "id": 21,
      "name": "laxmi Babysitting service",
      "service": "Babysitter",
      "price": 900,
      "catagory": "Driving for day",
      "imformation": "professional driving service by RazeJobfinder",
      "imformations": "Good babysitters"
    },
    {
      "id": 22,
      "name": "laxmi Babysitting service",
      "service": "Babysitter",
      "price": 900,
      "catagory": "Driving for day",
      "imformation": "professional driving service by RazeJobfinder",
      "imformations": "Good babysitters"
    },
    {
      "id": 23,
      "name": "laxmi Babysitting service",
      "service": "Babysitter",
      "price": 900,
      "catagory": "Driving for day",
      "imformation": "professional Babysitting service by RazeJobfinder",
      "imformations": "Good babysitters"
    },
    {
      "id": 24,
      "name": "laxmi Babysitting service",
      "service": "Babysitter",
      "price": 900,
      "catagory": "Driving for day",
      "imformation": "professional driving service by RazeJobfinder",
      "imformations": "Good babysitters"
    },
    {
      "id": 25,
      "name": "laxmi Babysitting service",
      "service": "Babysitter",
      "price": 900,
      "catagory": "Driving for day",
      "imformation": "professional driving service by RazeJobfinder",
      "imformations": "Good babysitters"
    },
    {
      "id": 26,
      "name": "laxmi Babysitting service",
      "service": "Babysitter",
      "price": 900,
      "catagory": "Driving for day",
      "imformation": "professional driving service by RazeJobfinder",
      "imformations": "Good babysitters"
    },
    {
      "id": 27,
      "name": "laxmi Babysitting service",
      "service": "Babysitter",
      "price": 900,
      "catagory": "Driving for day",
      "imformation": "professional driving service by RazeJobfinder",
      "imformations": "Good babysitters"
    },
    {
      "id": 28,
      "name": "laxmi Babysitting service",
      "service": "Babysitter",
      "price": 900,
      "catagory": "Driving for day",
      "imformation": "professional Babysitting service by RazeJobfinder",
      "imformations": "Good babysitters"
    },
    {
      "id": 29,
      "name": "laxmi Babysitting service",
      "service": "Babysitter",
      "price": 900,
      "catagory": "Driving for day",
      "imformation": "professional driving service by RazeJobfinder",
      "imformations": "Good babysitters"
    },
    {
      "id": 30,
      "name": "lack Babysitting service",
      "service": "Painter",
      "price": 900,
      "catagory": "Painter for day",
      "imformation": "professional Painter service by RazeJobfinder",
      "imformations": "Good Painter"
    },
    {
      "id": 31,
      "name": "life Painter service",
      "service": "Painter",
      "price": 900,
      "catagory": "Painter for day",
      "imformation": "professional Painter service by RazeJobfinder",
      "imformations": "Good Painter"
    },
    {
      "id": 32,
      "name": "leef Painter service",
      "service": "Painter",
      "price": "900",
      "catagory": "Painter for day",
      "imformation": "professional Painter service by RazeJobfinder",
      "imformations": "Good Painter"
    },
    {
      "id": 33,
      "name": "veek Painter service",
      "service": "Painter",
      "price": "900",
      "catagory": "Painter for day",
      "imformation": "professional Painter service by RazeJobfinder",
      "imformations": "Good Painter"
    },
    {
      "id": 34,
      "name": "lacky Painter service",
      "service": "Painter",
      "price": "900",
      "catagory": "Painter for day",
      "imformation": "professional Painter service by RazeJobfinder",
      "imformations": "Good Painter"
    },
    {
      "id": 35,
      "name": "vicky Painter service",
      "service": "Painter",
      "price": "900",
      "catagory": "Painter for day",
      "imformation": "professional Painter service by RazeJobfinder",
      "imformations": "Good Painter"
    },
    {
      "id": 36,
      "name": "laxmi Babysitting service",
      "service": "Painter",
      "price": "900",
      "catagory": "Painter for day",
      "imformation": "professional Painter service by RazeJobfinder",
      "imformations": "Good Painter"
    },
    {
      "name": "kash service",
      "service": "bathroom cleaning",
      "catagory": "home cleaning",
      "price": "600",
      "information": "bathroom cleaning is best cleaning for your home",
      "id": 37
    },
    {
      "id": 38,
      "name": "prem Painter service",
      "service": "Plumber",
      "price": "1000",
      "catagory": "Plumber for day",
      "imformation": "professional Plumber service by RazeJobfinder",
      "imformations": "Good plumber"
    },
    {
      "id": 39,
      "name": "lakshay Painter service",
      "service": "Plumber",
      "price": "1000",
      "catagory": "Plumber for day",
      "imformation": "professional Plumber service by RazeJobfinder",
      "imformations": "Good Plumber"
    },
    {
      "id": 40,
      "name": "fc Plumber service",
      "service": "Plumber",
      "price": "1000",
      "catagory": "Plumber for day",
      "imformation": "professional Plumber service by RazeJobfinder",
      "imformations": "Good Plumber"
    },
    {
      "id": 41,
      "name": "Csk Plumber service",
      "service": "Plumber",
      "price": "1000",
      "catagory": "Plumber for day",
      "imformation": "professional Plumber service by RazeJobfinder",
      "imformations": "Good Plumber"
    },
    {
      "id": 42,
      "name": "lucky Plumber service",
      "service": "Plumber",
      "price": "1000",
      "catagory": "Plumber for day",
      "imformation": "professional Plumber service by RazeJobfinder",
      "imformations": "Good Plumber"
    },
    {
      "id": 43,
      "name": "lucky Plumber service",
      "service": "Plumber",
      "price": "1000",
      "catagory": "Plumber for day",
      "imformation": "professional Plumber service by RazeJobfinder",
      "imformations": "Good Plumber"
    },
    {
      "id": 44,
      "name": "lucky Plumber service",
      "service": "Plumber",
      "price": "1000",
      "catagory": "Plumber for day",
      "imformation": "professional Plumber service by RazeJobfinder",
      "imformations": "Good Plumber"
    },
    {
      "id": 45,
      "name": "laxmi Plumber service",
      "service": "Plumber",
      "price": "600",
      "catagory": "Plumber for day",
      "imformation": "professional Plumber service by RazeJobfinder",
      "imformations": "Good Plumber"
    },

    {
      "id": 46,
      "name": "hardh service",
      "service": "Home Maid",
      "price": "600",
      "catagory": "Maid for day",
      "imformation": "professional Maid service by RazeJobfinder",
      "imformations": "Good Maid"
    },
    {
      "id": 47,
      "name": "lucky Maid service",
      "service": "Home Maid",
      "price": "600",
      "catagory": "Maid for day",
      "imformation": "professional Maid service by RazeJobfinder",
      "imformations": "Good Maid"
    },
    {
      "id": 48,
      "name": "laxmi Maid service",
      "service": "Home Maid",
      "price": "600",
      "catagory": "Plumber for day",
      "imformation": "professional Maid service by RazeJobfinder",
      "imformations": "Good Maid"
    },

    {
      "id": 49,
      "name": "luck Maid service",
      "service": "Home Maid",
      "price": "600",
      "catagory": "Plumber for day",
      "imformation": "professional Plumber service by RazeJobfinder",
      "imformations": "Good Maid"
    },
    {
      "id": 50,
      "name": "Fc Maid service",
      "service": "Home Maid",
      "price": "600",
      "catagory": "Plumber for day",
      "imformation": "professional Plumber service by RazeJobfinder",
      "imformations": "Good Maid"
    },
    {
      "id": 51,
      "name": " Maid Service",
      "service": "Home Maid",
      "price": "600",
      "catagory": "Plumber for day",
      "imformation": "professional Plumber service by RazeJobfinder",
      "imformations": "Good Maid"
    },

    {
      "id": 52,
      "name": "hardh Electrician service",
      "service": "Electrician",
      "price": "600",
      "catagory": "Electrician for day",
      "imformation": "professional Electrician service by RazeJobfinder",
      "imformations": "Good Electrician"
    },
    {
      "id": 53,
      "name": "lucky Electrician service",
      "service": "Electrician",
      "price": "600",
      "catagory": "Electrician for day",
      "imformation": "professional Electrician service by RazeJobfinder",
      "imformations": "Good Electrician"
    },
    {
      "id": 54,
      "name": "laxmi Electrician service",
      "service": "Electrician",
      "price": "600",
      "catagory": "Electrician for day",
      "imformation": "professional Electrician service by RazeJobfinder",
      "imformations": "Good Electrician"
    },

    {
      "id": 55,
      "name": "luck Electrician service",
      "service": "Electrician",
      "price": "600",
      "catagory": "Plumber for day",
      "imformation": "professional Electrician service by RazeJobfinder",
      "imformations": "Good Electrician"
    },
    {
      "id": 56,
      "name": "Fc Electrician service",
      "service": "Electrician",
      "price": "600",
      "catagory": "Electrician for day",
      "imformation": "professional Electrician service by RazeJobfinder",
      "imformations": "Good Electrician"
    },
    {
      "id": 57,
      "name": " Electrician Service",
      "service": "Electrician",
      "price": "600",
      "catagory": "Electrician for day",
      "imformation": "professional Electrician service by RazeJobfinder",
      "imformations": "Good Electrician"
    },
    {
      "id": 58,
      "name": " Bathroom Cleaning Service",
      "service": "Bathroomplumber",
      "price": "600",
      "catagory": "Plumber service",
      "imformation": "professional Cleaning service by RazeJobfinder",
      "imformations": "Good Cleaning"
    },
    {
      "id": 59,
      "name": "Bathroom Plumber Service",
      "service": "Bathroomplumber",
      "price": "600",
      "catagory": "Plumber service",
      "imformation": "professional Plumber service by RazeJobfinder",
      "imformations": "Good Cleaning"
    },
    {
      "id": 60,
      "name": "Kitchen Plumber  Service",
      "service": "KitchenPlumber",
      "price": "600",
      "catagory": "Plumber service",
      "imformation": "professional Plumber service by RazeJobfinder",
      "imformations": "Good Cleaning"
    },
    {
      "id": 61,
      "name": "Kitchen Plumber Service",
      "service": "KitchenPlumber",
      "price": "600",
      "catagory": "Plumber service",
      "imformation": "professional Plumber service by RazeJobfinder",
      "imformations": "Good Cleaning"
    },
    {
      "id": 62,
      "name": "Bathroom Cleaning Service",
      "service": "BathroomCleaning",
      "price": "400",
      "catagory": "Cleaning service",
      "imformation": "professional Cleaning service by RazeJobfinder",
      "imformations": "Good Cleaning"
    },
    {
      "id": 63,
      "name": "Bathroom Cleaning Service",
      "service": "BathroomCleaning",
      "price": "400",
      "catagory": "Cleaning service",
      "imformation": "professional Cleaning service by RazeJobfinder",
      "imformations": "Good Cleaning"
    },
    {
      "id": 64,
      "name": "Bathroom Cleaning Service",
      "service": "BathroomCleaning",
      "price": "400",
      "catagory": "Cleaning service",
      "imformation": "professional Cleaning service by RazeJobfinder",
      "imformations": "Good Cleaning"
    },
    {
      "id": 65,
      "name": "Leaf Cleaning Service",
      "service": "KitchenCleaning",
      "price": "400",
      "catagory": "Cleaning service",
      "imformation": "professional Cleaning service by RazeJobfinder",
      "imformations": "Good Cleaning"
    },
    {
      "id": 66,
      "name": "Leaf Cleaning Service",
      "service": "KitchenCleaning",
      "price": "400",
      "catagory": "Cleaning service",
      "imformation": "professional Cleaning service by RazeJobfinder",
      "imformations": "Good Cleaning"
    },
    {
      "id": 67,
      "name": "Leaf Cleaning Service",
      "service": "KitchenCleaning",
      "price": "400",
      "catagory": "Cleaning service",
      "imformation": "professional Cleaning service by RazeJobfinder",
      "imformations": "Good Cleaning"
    },
    {
      "id": 68,
      "name": "Loppy Cleaning Service",
      "service": "KitchenCleaning",
      "price": "400",
      "catagory": "Cleaning service",
      "imformation": "professional Cleaning service by RazeJobfinder",
      "imformations": "Good Cleaning"
    },
    {
      "id": 69,
      "name": "Leaf Cleaning Service",
      "service": "Oneroom",
      "price": "500",
      "catagory": " 1 Rk Cleaning service",
      "imformation": "professional Cleaning service by RazeJobfinder",
      "imformations": "Good Cleaning"
    },
    {
      "id": 70,
      "name": "Leaf Cleaning Service",
      "service": "Oneroom",
      "price": "500",
      "catagory": "1 Rk Cleaning service",
      "imformation": "professional Cleaning service by RazeJobfinder",
      "imformations": "Good Cleaning"
    },
    {
      "id": 71,
      "name": "Leaf Cleaning Service",
      "service": "Oneroom",
      "price": "500",
      "catagory": " 1 Rk Cleaning service",
      "imformation": "professional Cleaning service by RazeJobfinder",
      "imformations": "Good Cleaning"
    },
    {
      "id": 72,
      "name": "Loppy Cleaning Service",
      "service": "Oneroom",
      "price": "500",
      "catagory": " 1 Rk Cleaning service",
      "imformation": "professional Cleaning service by RazeJobfinder",
      "imformations": "Good Cleaning"
    },
    {
      "id": 73,
      "name": "Leaf Cleaning Service",
      "service": "Kitchenpainting",
      "price": "500",
      "catagory": "Painting service",
      "imformation": "professional Cleaning service by RazeJobfinder",
      "imformations": "Good Cleaning"
    },
    {
      "id": 74,
      "name": "Leaf Cleaning Service",
      "service": "Kitchenpainting",
      "price": "500",
      "catagory": "Painting service",
      "imformation": "professional Cleaning service by RazeJobfinder",
      "imformations": "Good Cleaning"
    },
    {
      "id": 75,
      "name": "Leaf Cleaning Service",
      "service": "Kitchenpainting",
      "price": "500",
      "catagory": " Paintingservice",
      "imformation": "professional Cleaning service by RazeJobfinder",
      "imformations": "Good Cleaning"
    },
    {
      "id": 76,
      "name": "Loppy Cleaning Service",
      "service": "Kitchenpainting",
      "price": "500",
      "catagory": "Painting service",
      "imformation": "professional Cleaning service by RazeJobfinder",
      "imformations": "Good Cleaning"
    }


















  ]
}